setup.py
distributions/Binomialdistribution.py
distributions/Gaussiandistribution.py
distributions/Generaldistribution.py
distributions/__init__.py
vu12_distributions.egg-info/PKG-INFO
vu12_distributions.egg-info/SOURCES.txt
vu12_distributions.egg-info/dependency_links.txt
vu12_distributions.egg-info/not-zip-safe
vu12_distributions.egg-info/top_level.txt